azext_identitycertificatebasedauthconfiguration/__init__.py
azext_identitycertificatebasedauthconfiguration/action.py
azext_identitycertificatebasedauthconfiguration/azext_metadata.json
azext_identitycertificatebasedauthconfiguration/custom.py
azext_identitycertificatebasedauthconfiguration/generated/__init__.py
azext_identitycertificatebasedauthconfiguration/generated/_client_factory.py
azext_identitycertificatebasedauthconfiguration/generated/_help.py
azext_identitycertificatebasedauthconfiguration/generated/_params.py
azext_identitycertificatebasedauthconfiguration/generated/_validators.py
azext_identitycertificatebasedauthconfiguration/generated/action.py
azext_identitycertificatebasedauthconfiguration/generated/commands.py
azext_identitycertificatebasedauthconfiguration/generated/custom.py
azext_identitycertificatebasedauthconfiguration/manual/__init__.py
azext_identitycertificatebasedauthconfiguration/tests/__init__.py
azext_identitycertificatebasedauthconfiguration/tests/latest/__init__.py
azext_identitycertificatebasedauthconfiguration/tests/latest/test_identitycertificatebasedauthconfiguration_scenario.py
azext_identitycertificatebasedauthconfiguration/vendored_sdks/__init__.py
azext_identitycertificatebasedauthconfiguration/vendored_sdks/identitycertificatebasedauthconfiguration/__init__.py
azext_identitycertificatebasedauthconfiguration/vendored_sdks/identitycertificatebasedauthconfiguration/_configuration.py
azext_identitycertificatebasedauthconfiguration/vendored_sdks/identitycertificatebasedauthconfiguration/_identity_certificate_based_auth_configuration.py
azext_identitycertificatebasedauthconfiguration/vendored_sdks/identitycertificatebasedauthconfiguration/aio/__init__.py
azext_identitycertificatebasedauthconfiguration/vendored_sdks/identitycertificatebasedauthconfiguration/aio/_configuration_async.py
identitycertificatebasedauthconfiguration-0.1.0.dist-info/METADATA
identitycertificatebasedauthconfiguration-0.1.0.dist-info/WHEEL
identitycertificatebasedauthconfiguration-0.1.0.dist-info/top_level.txt
identitycertificatebasedauthconfiguration-0.1.0.dist-info/RECORD
