Metadata-Version: 2.1
Name: identitycertificatebasedauthconfiguration
Version: 0.1.0
Summary: Microsoft Azure Command-Line Tools IdentityCertificateBasedAuthConfiguration Extension
Home-page: https://github.com/Azure/azure-cli-extensions/tree/master/src/identitycertificatebasedauthconfiguration
Author: Microsoft Corporation
Author-email: azpycli@microsoft.com
License: MIT
